laborit_heigen/__init__.py
laborit_heigen/main.py
laborit_heigen-0.1.dist-info/METADATA
laborit_heigen-0.1.dist-info/WHEEL
laborit_heigen-0.1.dist-info/top_level.txt
laborit_heigen-0.1.dist-info/RECORD
