Metadata-Version: 2.1
Name: laborit-heigen
Version: 0.1
Requires-Dist: langchain
Requires-Dist: langchain-core
